social_media_url_extractor/__init__.py
social_media_url_extractor/cli.py
social_media_url_extractor/extractor.py
social_media_url_extractor-0.1.1.dist-info/LICENSE
social_media_url_extractor-0.1.1.dist-info/METADATA
social_media_url_extractor-0.1.1.dist-info/WHEEL
social_media_url_extractor-0.1.1.dist-info/entry_points.txt
social_media_url_extractor-0.1.1.dist-info/top_level.txt
social_media_url_extractor-0.1.1.dist-info/RECORD
